setup.py
cubefilter/__init__.py
cubefilter/cubefilter.py
cubefilter/cubefilter_tests.py
cubefilter.egg-info/PKG-INFO
cubefilter.egg-info/SOURCES.txt
cubefilter.egg-info/dependency_links.txt
cubefilter.egg-info/not-zip-safe
cubefilter.egg-info/top_level.txt