Metadata-Version: 1.0
Name: cubefilter
Version: 0.0.1
Summary: Python backend for cubefilter: it precomputes OLAP cubes and allows to used them in dc.js.
Home-page: https://github.com/markus1978/cubefilter
Author: Markus Scheidgen
Author-email: markus.scheidgen@gmail.com
License: MIT
Platform: UNKNOWN
